_p2pExtension.cpython-39-i386-linux-gnu.so
spatial_access-1.0.2.dist-info/METADATA
spatial_access-1.0.2.dist-info/WHEEL
spatial_access-1.0.2.dist-info/RECORD
spatial_access-1.0.2.dist-info/top_level.txt
spatial_access/BaseModel.py
spatial_access/__init__.py
spatial_access/_parsers.py
spatial_access/Models.py
spatial_access/Configs.py
spatial_access/NetworkInterface.py
spatial_access/SpatialAccessExceptions.py
spatial_access/p2p.py
spatial_access/MatrixInterface.py
