Metadata-Version: 2.1
Name: spatial_access
Version: 1.0.2
Summary: UNKNOWN
Home-page: https://github.com/GeoDaCenter/spatial_access
Author: Logan Noel (lmnoel), Xun Li
Author-email: lnoel@uchicago.edu
License: BSD
Platform: UNKNOWN
